rtl/sysctrl.v
// System control registers (32-bit accesses only)
//   +0x0  BOOT : read bit0 = ROM overlay at 0x0 active; ANY write clears it
//   +0x4  ID   : read-only 0x03030001
//   +0x8  LEDS : read/write [3:0]
module sysctrl (
    input  wire        clk,
    input  wire        rst_n,
    input  wire        req,
    input  wire        sel,
    input  wire        we,
    input  wire [1:0]  reg_a,            // addr[3:2]
    input  wire [31:0] wdata,
    output reg  [31:0] rdata,
    output reg         ack,
    output reg         overlay,
    output reg  [3:0]  leds
);
    wire go = req & sel & ~ack;
    always @(posedge clk) begin
        if (!rst_n) begin
            ack     <= 1'b0;
            overlay <= 1'b1;             // ROM appears at 0x0 after reset
            leds    <= 4'd0;
        end else begin
            ack <= go;
            if (go && we) begin
                case (reg_a)
                    2'd0: overlay <= 1'b0;
                    2'd2: leds    <= wdata[3:0];
                    default: ;
                endcase
            end
        end
        case (reg_a)
            2'd0:    rdata <= {31'd0, overlay};
            2'd1:    rdata <= 32'h0303_0001;
            2'd2:    rdata <= {28'd0, leds};
            default: rdata <= 32'd0;
        endcase
    end
endmodule

rtl/uart.v
// Minimal 8N1 UART (32-bit accesses only)
//   +0x0 DATA   : write [7:0] = transmit; read [7:0] = received byte (clears rx_valid)
//   +0x4 STATUS : read bit0 = tx_ready, bit1 = rx_valid
module uart #(
    parameter CLK_HZ = 50_000_000,
    parameter BAUD   = 115_200
)(
    input  wire        clk,
    input  wire        rst_n,
    input  wire        req,
    input  wire        sel,
    input  wire        we,
    input  wire        reg_a,            // addr[2]
    input  wire [31:0] wdata,
    output reg  [31:0] rdata,
    output reg         ack,
    input  wire        rxd,
    output wire        txd
);
    localparam integer DIV = CLK_HZ / BAUD;

    wire go = req & sel & ~ack;

    // ---------------- TX ----------------
    reg [9:0]  tx_shift;
    reg [3:0]  tx_cnt;
    reg [15:0] tx_div;
    reg        tx_busy;
    assign txd = tx_busy ? tx_shift[0] : 1'b1;

    // ---------------- RX ----------------
    reg [1:0]  rx_sr;
    reg        rx_busy;
    reg [15:0] rx_div;
    reg [3:0]  rx_cnt;
    reg [7:0]  rx_sh, rx_data;
    reg        rx_valid;
    wire       rxs = rx_sr[1];

    always @(posedge clk) begin
        if (!rst_n) begin
            ack <= 1'b0;
            tx_busy <= 1'b0; tx_shift <= 10'h3FF; tx_cnt <= 4'd0; tx_div <= 16'd0;
            rx_sr <= 2'b11; rx_busy <= 1'b0; rx_div <= 16'd0; rx_cnt <= 4'd0;
            rx_sh <= 8'd0; rx_data <= 8'd0; rx_valid <= 1'b0;
        end else begin
            ack   <= go;
            rx_sr <= {rx_sr[0], rxd};

            // TX engine
            if (tx_busy) begin
                if (tx_div == DIV-1) begin
                    tx_div   <= 16'd0;
                    tx_shift <= {1'b1, tx_shift[9:1]};
                    if (tx_cnt == 4'd9) tx_busy <= 1'b0;
                    else                tx_cnt  <= tx_cnt + 4'd1;
                end else tx_div <= tx_div + 16'd1;
            end else if (go && we && !reg_a) begin
                tx_shift <= {1'b1, wdata[7:0], 1'b0};   // stop, data, start
                tx_busy  <= 1'b1;
                tx_cnt   <= 4'd0;
                tx_div   <= 16'd0;
            end

            // Clear rx_valid on data read (set below wins if a byte lands now)
            if (go && !we && !reg_a) rx_valid <= 1'b0;

            // RX engine
            if (!rx_busy) begin
                if (!rxs) begin                          // start bit edge
                    rx_busy <= 1'b1;
                    rx_div  <= DIV/2;                    // -> middle of start bit
                    rx_cnt  <= 4'd0;
                end
            end else if (rx_div != 0) begin
                rx_div <= rx_div - 16'd1;
            end else begin
                rx_div <= DIV-1;
                if (rx_cnt == 4'd0) begin
                    if (rxs) rx_busy <= 1'b0;            // glitch, abort
                    else     rx_cnt  <= 4'd1;
                end else if (rx_cnt <= 4'd8) begin
                    rx_sh  <= {rxs, rx_sh[7:1]};         // LSB first
                    rx_cnt <= rx_cnt + 4'd1;
                end else begin                           // stop bit
                    rx_data  <= rx_sh;
                    rx_valid <= 1'b1;
                    rx_busy  <= 1'b0;
                end
            end
        end
        rdata <= reg_a ? {30'd0, rx_valid, ~tx_busy} : {24'd0, rx_data};
    end
endmodule

rtl/ram_bram.v
// Bring-up RAM in block RAM with byte enables (4 byte-wide banks).
// Replace with an SDRAM controller once the CPU boots (same internal-bus ports).
module ram_bram #(
    parameter AW = 13                    // words -> 8192 x 4 = 32 KB
)(
    input  wire          clk,
    input  wire          rst_n,
    input  wire          req,
    input  wire          sel,
    input  wire          we,
    input  wire [3:0]    be,
    input  wire [AW-1:0] a,
    input  wire [31:0]   wdata,
    output reg  [31:0]   rdata,
    output reg           ack
);
    reg [7:0] m3 [0:(1<<AW)-1];         // D[31:24]
    reg [7:0] m2 [0:(1<<AW)-1];         // D[23:16]
    reg [7:0] m1 [0:(1<<AW)-1];         // D[15:8]
    reg [7:0] m0 [0:(1<<AW)-1];         // D[7:0]

    wire go = req & sel & ~ack;
    always @(posedge clk) begin
        if (!rst_n) ack <= 1'b0; else ack <= go;
        if (go && we) begin
            if (be[3]) m3[a] <= wdata[31:24];
            if (be[2]) m2[a] <= wdata[23:16];
            if (be[1]) m1[a] <= wdata[15:8];
            if (be[0]) m0[a] <= wdata[7:0];
        end
        rdata <= {m3[a], m2[a], m1[a], m0[a]};
    end
endmodule

rtl/rom.v
// Boot ROM (block RAM initialised from a hex file, one 32-bit word per line).
module rom #(
    parameter AW   = 12,                 // words -> 4096 x 4 = 16 KB
    parameter INIT = "fw/boot.hex"
)(
    input  wire          clk,
    input  wire          rst_n,
    input  wire          req,
    input  wire          sel,
    input  wire [AW-1:0] a,              // word address
    output reg  [31:0]   rdata,
    output reg           ack
);
    reg [31:0] mem [0:(1<<AW)-1];
    initial $readmemh(INIT, mem);

    wire go = req & sel & ~ack;
    always @(posedge clk) begin
        if (!rst_n) ack <= 1'b0; else ack <= go;
        rdata <= mem[a];
    end
endmodule

rtl/bus_bridge.v
// -----------------------------------------------------------------------------
// bus_bridge.v  --  68030 asynchronous bus  <->  simple internal bus
//
// This is the ONLY CPU-specific module. Swap it out to change CPUs.
//
// Internal bus protocol (all synchronous to clk, which should be >= 2x CPU clk):
//   - bridge raises `req` and holds addr/we/be/wdata stable
//   - the selected slave answers with a ONE-cycle `ack` pulse, rdata valid then
//   - bridge drops `req` the cycle after it sees `ack`
//   - no ack within 256 clk cycles  ->  BERR* to the CPU (unmapped address)
//
// be[3] = D[31:24] ... be[0] = D[7:0]   (68030 big-endian byte lanes)
// All ports are presented to the CPU as 32-bit (DSACK1*=DSACK0*=0).
// -----------------------------------------------------------------------------
module bus_bridge (
    input  wire        clk,
    input  wire        rst_n,

    // 68030 side
    input  wire [31:0] cpu_a,
    input  wire [31:0] cpu_d_in,
    output reg  [31:0] cpu_d_out,
    output reg         cpu_d_oe,
    input  wire        cpu_as_n,
    input  wire        cpu_ds_n,
    input  wire        cpu_rw,          // 1 = read, 0 = write
    input  wire [1:0]  cpu_siz,
    output reg  [1:0]  cpu_dsack_n,
    output reg         cpu_berr_n,

    // internal bus (master side)
    output reg         req,
    output reg         we,
    output reg  [31:0] addr,
    output reg  [31:0] wdata,
    output reg  [3:0]  be,
    input  wire [31:0] rdata,
    input  wire        ack
);

    // Synchronise the async strobes (active-low -> active-high)
    reg [1:0] as_sr, ds_sr;
    always @(posedge clk or negedge rst_n) begin
        if (!rst_n) begin
            as_sr <= 2'b00;
            ds_sr <= 2'b00;
        end else begin
            as_sr <= {as_sr[0], ~cpu_as_n};
            ds_sr <= {ds_sr[0], ~cpu_ds_n};
        end
    end
    wire as_s = as_sr[1];
    wire ds_s = ds_sr[1];

    // Byte enables from SIZ[1:0] and A[1:0] for a 32-bit port
    reg [3:0] be_c;
    always @* begin
        case (cpu_siz)
            2'b01: case (cpu_a[1:0])                 // byte
                       2'b00: be_c = 4'b1000;
                       2'b01: be_c = 4'b0100;
                       2'b10: be_c = 4'b0010;
                       2'b11: be_c = 4'b0001;
                   endcase
            2'b10: case (cpu_a[1:0])                 // word
                       2'b00: be_c = 4'b1100;
                       2'b01: be_c = 4'b0110;
                       2'b10: be_c = 4'b0011;
                       2'b11: be_c = 4'b0001;
                   endcase
            2'b11: case (cpu_a[1:0])                 // 3 bytes
                       2'b00: be_c = 4'b1110;
                       2'b01: be_c = 4'b0111;
                       2'b10: be_c = 4'b0011;
                       2'b11: be_c = 4'b0001;
                   endcase
            default: case (cpu_a[1:0])               // long
                       2'b00: be_c = 4'b1111;
                       2'b01: be_c = 4'b0111;
                       2'b10: be_c = 4'b0011;
                       2'b11: be_c = 4'b0001;
                   endcase
        endcase
    end

    localparam S_IDLE = 2'd0, S_WAIT = 2'd1, S_DONE = 2'd2;
    reg [1:0] st;
    reg [7:0] tmo;

    always @(posedge clk or negedge rst_n) begin
        if (!rst_n) begin
            st          <= S_IDLE;
            req         <= 1'b0;
            we          <= 1'b0;
            addr        <= 32'd0;
            wdata       <= 32'd0;
            be          <= 4'd0;
            tmo         <= 8'd0;
            cpu_d_out   <= 32'd0;
            cpu_d_oe    <= 1'b0;
            cpu_dsack_n <= 2'b11;
            cpu_berr_n  <= 1'b1;
        end else begin
            case (st)
            S_IDLE: begin
                // Reads can start on AS*; writes wait for DS* (data valid)
                if (as_s && (cpu_rw || ds_s)) begin
                    addr  <= cpu_a;
                    we    <= ~cpu_rw;
                    be    <= be_c;
                    wdata <= cpu_d_in;
                    req   <= 1'b1;
                    tmo   <= 8'd0;
                    st    <= S_WAIT;
                end
            end
            S_WAIT: begin
                tmo <= tmo + 8'd1;
                if (!as_s) begin                 // CPU aborted the cycle
                    req <= 1'b0;
                    st  <= S_IDLE;
                end else if (ack) begin
                    req         <= 1'b0;
                    cpu_d_out   <= rdata;
                    cpu_d_oe    <= cpu_rw;
                    cpu_dsack_n <= 2'b00;        // 32-bit port termination
                    st          <= S_DONE;
                end else if (&tmo) begin         // nobody answered
                    req        <= 1'b0;
                    cpu_berr_n <= 1'b0;
                    st         <= S_DONE;
                end
            end
            S_DONE: begin
                if (!as_s) begin
                    cpu_dsack_n <= 2'b11;
                    cpu_berr_n  <= 1'b1;
                    cpu_d_oe    <= 1'b0;
                    st          <= S_IDLE;
                end
            end
            default: st <= S_IDLE;
            endcase
        end
    end
endmodule

rtl/top.v
// -----------------------------------------------------------------------------
// top.v -- minimal 68030 SoC glue
//
// Memory map (see README.md):
//   0x0000_0000  RAM (bring-up: 32 KB BRAM; later SDRAM)   [ROM overlay at reset]
//   0xFD00_0000  VRAM      (reserved)
//   0xFE00_0000  UART
//   0xFE00_1000  SYSCTRL
//   0xFE00_2000  SCSI      (reserved)
//   0xFE00_3000  VIDEO regs(reserved)
//   0xFFF0_0000  Boot ROM (16 KB, mirrored across 1 MB)
// -----------------------------------------------------------------------------
module top #(
    parameter CLK_HZ = 50_000_000,
    parameter BAUD   = 115_200,
    parameter ROM_INIT = "fw/boot.hex"
)(
    input  wire        clk50,            // FPGA oscillator; CPU clock = clk50 / 2
    input  wire        rst_btn_n,

    // ---- 68030 pins (use level shifters: 68030 is 5 V, FPGA is 3.3 V or less)
    output wire        cpu_clk,
    output wire        cpu_reset_n,
    output wire        cpu_halt_n,
    input  wire [31:0] cpu_a,
    inout  wire [31:0] cpu_d,
    input  wire        cpu_as_n,
    input  wire        cpu_ds_n,
    input  wire        cpu_rw,
    input  wire [1:0]  cpu_siz,
    output wire [1:0]  cpu_dsack_n,
    output wire        cpu_berr_n,
    // tie-offs for inputs we don't use yet
    output wire [2:0]  cpu_ipl_n,        // no interrupts
    output wire        cpu_avec_n,
    output wire        cpu_sterm_n,      // no synchronous/burst termination
    output wire        cpu_ciin_n,       // TODO: assert for I/O regions
    output wire        cpu_br_n,         // no other bus masters
    output wire        cpu_bgack_n,

    // ---- board peripherals
    output wire        uart_txd,
    input  wire        uart_rxd,
    output wire [3:0]  leds
);

    // ---- CPU clock and power-on reset --------------------------------------
    reg cpu_clk_r = 1'b0;
    always @(posedge clk50) cpu_clk_r <= ~cpu_clk_r;
    assign cpu_clk = cpu_clk_r;

    reg [15:0] rst_cnt = 16'd0;          // ~1.3 ms at 50 MHz (68030 wants >= 520 CPU clocks)
    reg        rst_n_r = 1'b0;
    always @(posedge clk50) begin
        if (!rst_btn_n) begin
            rst_cnt <= 16'd0;
            rst_n_r <= 1'b0;
        end else if (rst_cnt != 16'hFFFF) begin
            rst_cnt <= rst_cnt + 16'd1;
        end else begin
            rst_n_r <= 1'b1;
        end
    end
    wire rst_n = rst_n_r;
    assign cpu_reset_n = rst_n;
    assign cpu_halt_n  = rst_n;

    assign cpu_ipl_n   = 3'b111;
    assign cpu_avec_n  = 1'b1;
    assign cpu_sterm_n = 1'b1;
    assign cpu_ciin_n  = 1'b1;
    assign cpu_br_n    = 1'b1;
    assign cpu_bgack_n = 1'b1;

    // ---- CPU bridge ----------------------------------------------------------
    wire [31:0] cpu_d_out;
    wire        cpu_d_oe;
    assign cpu_d = cpu_d_oe ? cpu_d_out : 32'bz;

    wire        req, we, ack;
    wire [31:0] addr, wdata, rdata;
    wire [3:0]  be;

    bus_bridge u_bridge (
        .clk(clk50), .rst_n(rst_n),
        .cpu_a(cpu_a), .cpu_d_in(cpu_d), .cpu_d_out(cpu_d_out), .cpu_d_oe(cpu_d_oe),
        .cpu_as_n(cpu_as_n), .cpu_ds_n(cpu_ds_n), .cpu_rw(cpu_rw), .cpu_siz(cpu_siz),
        .cpu_dsack_n(cpu_dsack_n), .cpu_berr_n(cpu_berr_n),
        .req(req), .we(we), .addr(addr), .wdata(wdata), .be(be),
        .rdata(rdata), .ack(ack)
    );

    // ---- address decode ------------------------------------------------------
    wire overlay;
    wire sel_rom  = (addr[31:20] == 12'hFFF) || (overlay && addr[31:20] == 12'h000);
    wire sel_ram  = !overlay && (addr[31:15] == 17'd0);            // 32 KB for now
    wire sel_io   = (addr[31:16] == 16'hFE00);
    wire sel_uart = sel_io && (addr[15:12] == 4'h0);
    wire sel_sys  = sel_io && (addr[15:12] == 4'h1);
    // sel_scsi = sel_io && addr[15:12]==4'h2;   -- TODO
    // sel_vid  = sel_io && addr[15:12]==4'h3;   -- TODO

    // ---- slaves --------------------------------------------------------------
    wire [31:0] rom_rd, ram_rd, uart_rd, sys_rd;
    wire        rom_ack, ram_ack, uart_ack, sys_ack;

    rom #(.AW(12), .INIT(ROM_INIT)) u_rom (
        .clk(clk50), .rst_n(rst_n), .req(req), .sel(sel_rom),
        .a(addr[13:2]), .rdata(rom_rd), .ack(rom_ack));

    ram_bram #(.AW(13)) u_ram (
        .clk(clk50), .rst_n(rst_n), .req(req), .sel(sel_ram), .we(we), .be(be),
        .a(addr[14:2]), .wdata(wdata), .rdata(ram_rd), .ack(ram_ack));

    uart #(.CLK_HZ(CLK_HZ), .BAUD(BAUD)) u_uart (
        .clk(clk50), .rst_n(rst_n), .req(req), .sel(sel_uart), .we(we),
        .reg_a(addr[2]), .wdata(wdata), .rdata(uart_rd), .ack(uart_ack),
        .rxd(uart_rxd), .txd(uart_txd));

    sysctrl u_sys (
        .clk(clk50), .rst_n(rst_n), .req(req), .sel(sel_sys), .we(we),
        .reg_a(addr[3:2]), .wdata(wdata), .rdata(sys_rd), .ack(sys_ack),
        .overlay(overlay), .leds(leds));

    // ---- read-data / ack mux -------------------------------------------------
    assign ack   = rom_ack | ram_ack | uart_ack | sys_ack;
    assign rdata = rom_ack  ? rom_rd  :
                   ram_ack  ? ram_rd  :
                   uart_ack ? uart_rd :
                   sys_ack  ? sys_rd  : 32'd0;
endmodule

sim/tb_top.v
// Bus-functional testbench: plays the role of a 68030 and pokes the SoC.
// Run:  make sim     (needs Icarus Verilog)
`timescale 1ns/1ps
module tb;
    reg clk50 = 0;
    always #10 clk50 = ~clk50;           // 50 MHz

    reg         rst_btn_n = 0;
    reg  [31:0] a = 0, dv = 0;
    reg         doe = 0, as_n = 1, ds_n = 1, rw = 1;
    reg  [1:0]  siz = 0;
    wire [31:0] d = doe ? dv : 32'bz;

    wire [1:0]  dsack_n;
    wire        berr_n, cpu_clk, cpu_reset_n, cpu_halt_n, txd;
    wire [2:0]  ipl_n;
    wire        avec_n, sterm_n, ciin_n, br_n, bgack_n;
    wire [3:0]  leds;

    top #(.BAUD(5_000_000)) dut (           // fast UART for simulation (DIV = 10)
        .clk50(clk50), .rst_btn_n(rst_btn_n),
        .cpu_clk(cpu_clk), .cpu_reset_n(cpu_reset_n), .cpu_halt_n(cpu_halt_n),
        .cpu_a(a), .cpu_d(d), .cpu_as_n(as_n), .cpu_ds_n(ds_n), .cpu_rw(rw),
        .cpu_siz(siz), .cpu_dsack_n(dsack_n), .cpu_berr_n(berr_n),
        .cpu_ipl_n(ipl_n), .cpu_avec_n(avec_n), .cpu_sterm_n(sterm_n),
        .cpu_ciin_n(ciin_n), .cpu_br_n(br_n), .cpu_bgack_n(bgack_n),
        .uart_txd(txd), .uart_rxd(1'b1), .leds(leds));

    integer     errors = 0;
    reg [31:0]  rd;
    reg         got_berr;

    // One 68030-style bus cycle
    task cycle(input [31:0] addr, input is_read, input [1:0] size, input [31:0] wdat);
        integer n;
        begin
            a = addr; rw = is_read; siz = size; got_berr = 0;
            @(posedge clk50); #1;
            as_n = 0;
            if (!is_read) begin dv = wdat; doe = 1; end
            #1 ds_n = 0;
            n = 0;
            while (dsack_n == 2'b11 && berr_n == 1'b1 && n < 2000) begin
                @(posedge clk50); n = n + 1;
            end
            #1;
            rd = d;
            got_berr = (berr_n == 1'b0);
            as_n = 1; ds_n = 1; doe = 0;
            repeat (4) @(posedge clk50);      // let the bridge return to idle
        end
    endtask

    task check(input [255:0] name, input [31:0] got, input [31:0] exp);
        begin
            if (got !== exp) begin
                $display("FAIL %0s: got %h expected %h", name, got, exp);
                errors = errors + 1;
            end else $display("ok   %0s", name);
        end
    endtask

    // Very small UART receiver (200 ns bit time)
    reg [7:0] uart_rx = 0;
    reg       uart_got = 0;
    integer   i;
    always @(negedge txd) if (cpu_reset_n) begin
        #300;
        for (i = 0; i < 8; i = i + 1) begin uart_rx[i] = txd; #200; end
        uart_got = 1;
    end

    initial begin
        $dumpfile("sim/tb.vcd");
        $dumpvars(0, tb);
        #100 rst_btn_n = 1;
        wait (cpu_reset_n === 1'b1);
        repeat (10) @(posedge clk50);

        // Reset vectors visible at 0x0 through the ROM overlay
        cycle(32'h0000_0000, 1, 2'b00, 0);        check("overlay: SSP vector", rd, 32'h0000_8000);
        cycle(32'hFFF0_0004, 1, 2'b00, 0);        check("ROM alias: PC vector", rd, 32'hFFF0_0400);

        // Drop the overlay
        cycle(32'hFE00_1000, 1, 2'b00, 0);        check("BOOT reads overlay=1", rd, 32'd1);
        cycle(32'hFE00_1000, 0, 2'b00, 32'd0);
        cycle(32'hFE00_1000, 1, 2'b00, 0);        check("BOOT reads overlay=0", rd, 32'd0);
        cycle(32'hFE00_1004, 1, 2'b00, 0);        check("SYS ID", rd, 32'h0303_0001);

        // RAM long / byte / word writes
        cycle(32'h0000_0100, 0, 2'b00, 32'hDEAD_BEEF);
        cycle(32'h0000_0100, 1, 2'b00, 0);        check("RAM long r/w", rd, 32'hDEAD_BEEF);
        cycle(32'h0000_0101, 0, 2'b01, 32'h00AA_0000);
        cycle(32'h0000_0100, 1, 2'b00, 0);        check("RAM byte write A=1", rd, 32'hDEAA_BEEF);
        cycle(32'h0000_0102, 0, 2'b10, 32'h0000_1234);
        cycle(32'h0000_0100, 1, 2'b00, 0);        check("RAM word write A=2", rd, 32'hDEAA_1234);

        // Unmapped address -> BERR, and the bus must recover afterwards
        cycle(32'h5000_0000, 1, 2'b00, 0);        check("unmapped -> BERR", {31'd0, got_berr}, 32'd1);
        cycle(32'h0000_0100, 1, 2'b00, 0);        check("recovered after BERR", rd, 32'hDEAA_1234);

        // UART transmit
        cycle(32'hFE00_0000, 0, 2'b00, 32'h0000_0041);
        #4000;
        check("UART sent 'A'", {31'd0, uart_got}, 32'd1);
        check("UART byte",     {24'd0, uart_rx}, 32'h41);
        cycle(32'hFE00_0004, 1, 2'b00, 0);        check("UART tx_ready", rd & 32'h1, 32'd1);

        if (errors == 0) $display("ALL TESTS PASSED"); else $display("%0d TEST(S) FAILED", errors);
        $finish;
    end

    initial begin #5_000_000; $display("TIMEOUT"); $finish; end
endmodule

sim/tb.vcd
$date
	Wed Sep 30 13:47:26 2026
$end
$version
	Icarus Verilog
$end
$timescale
	1ps
$end
$scope module tb $end
$var wire 1 ! avec_n $end
$var wire 1 " bgack_n $end
$var wire 1 # br_n $end
$var wire 1 $ ciin_n $end
$var wire 32 % d [31:0] $end
$var wire 3 & ipl_n [2:0] $end
$var wire 1 ' sterm_n $end
$var wire 1 ( txd $end
$var wire 4 ) leds [3:0] $end
$var wire 2 * dsack_n [1:0] $end
$var wire 1 + cpu_reset_n $end
$var wire 1 , cpu_halt_n $end
$var wire 1 - cpu_clk $end
$var wire 1 . berr_n $end
$var reg 32 / a [31:0] $end
$var reg 1 0 as_n $end
$var reg 1 1 clk50 $end
$var reg 1 2 doe $end
$var reg 1 3 ds_n $end
$var reg 32 4 dv [31:0] $end
$var reg 1 5 got_berr $end
$var reg 32 6 rd [31:0] $end
$var reg 1 7 rst_btn_n $end
$var reg 1 8 rw $end
$var reg 2 9 siz [1:0] $end
$var reg 1 : uart_got $end
$var reg 8 ; uart_rx [7:0] $end
$var integer 32 < errors [31:0] $end
$var integer 32 = i [31:0] $end
$scope module dut $end
$var wire 1 > ack $end
$var wire 1 1 clk50 $end
$var wire 32 ? cpu_a [31:0] $end
$var wire 1 0 cpu_as_n $end
$var wire 1 ! cpu_avec_n $end
$var wire 1 " cpu_bgack_n $end
$var wire 1 # cpu_br_n $end
$var wire 1 $ cpu_ciin_n $end
$var wire 1 - cpu_clk $end
$var wire 32 @ cpu_d [31:0] $end
$var wire 1 3 cpu_ds_n $end
$var wire 1 , cpu_halt_n $end
$var wire 3 A cpu_ipl_n [2:0] $end
$var wire 1 + cpu_reset_n $end
$var wire 1 8 cpu_rw $end
$var wire 2 B cpu_siz [1:0] $end
$var wire 1 ' cpu_sterm_n $end
$var wire 1 7 rst_btn_n $end
$var wire 1 C sel_ram $end
$var wire 1 D sel_rom $end
$var wire 1 E sel_sys $end
$var wire 1 F sel_uart $end
$var wire 1 G uart_rxd $end
$var wire 1 H we $end
$var wire 32 I wdata [31:0] $end
$var wire 1 ( uart_txd $end
$var wire 32 J uart_rd [31:0] $end
$var wire 1 K uart_ack $end
$var wire 32 L sys_rd [31:0] $end
$var wire 1 M sys_ack $end
$var wire 1 N sel_io $end
$var wire 1 O rst_n $end
$var wire 32 P rom_rd [31:0] $end
$var wire 1 Q rom_ack $end
$var wire 1 R req $end
$var wire 32 S rdata [31:0] $end
$var wire 32 T ram_rd [31:0] $end
$var wire 1 U ram_ack $end
$var wire 1 V overlay $end
$var wire 4 W leds [3:0] $end
$var wire 2 X cpu_dsack_n [1:0] $end
$var wire 32 Y cpu_d_out [31:0] $end
$var wire 1 Z cpu_d_oe $end
$var wire 1 . cpu_berr_n $end
$var wire 4 [ be [3:0] $end
$var wire 32 \ addr [31:0] $end
$var parameter 32 ] BAUD $end
$var parameter 32 ^ CLK_HZ $end
$var parameter 88 _ ROM_INIT $end
$var reg 1 ` cpu_clk_r $end
$var reg 16 a rst_cnt [15:0] $end
$var reg 1 O rst_n_r $end
$scope module u_bridge $end
$var wire 1 > ack $end
$var wire 1 1 clk $end
$var wire 32 b cpu_a [31:0] $end
$var wire 1 0 cpu_as_n $end
$var wire 32 c cpu_d_in [31:0] $end
$var wire 1 3 cpu_ds_n $end
$var wire 1 8 cpu_rw $end
$var wire 2 d cpu_siz [1:0] $end
$var wire 32 e rdata [31:0] $end
$var wire 1 O rst_n $end
$var wire 1 f ds_s $end
$var wire 1 g as_s $end
$var parameter 2 h S_DONE $end
$var parameter 2 i S_IDLE $end
$var parameter 2 j S_WAIT $end
$var reg 32 k addr [31:0] $end
$var reg 2 l as_sr [1:0] $end
$var reg 4 m be [3:0] $end
$var reg 4 n be_c [3:0] $end
$var reg 1 . cpu_berr_n $end
$var reg 1 Z cpu_d_oe $end
$var reg 32 o cpu_d_out [31:0] $end
$var reg 2 p cpu_dsack_n [1:0] $end
$var reg 2 q ds_sr [1:0] $end
$var reg 1 R req $end
$var reg 2 r st [1:0] $end
$var reg 8 s tmo [7:0] $end
$var reg 32 t wdata [31:0] $end
$var reg 1 H we $end
$upscope $end
$scope module u_ram $end
$var wire 13 u a [12:0] $end
$var wire 4 v be [3:0] $end
$var wire 1 1 clk $end
$var wire 1 w go $end
$var wire 1 R req $end
$var wire 1 O rst_n $end
$var wire 1 C sel $end
$var wire 32 x wdata [31:0] $end
$var wire 1 H we $end
$var parameter 32 y AW $end
$var reg 1 U ack $end
$var reg 32 z rdata [31:0] $end
$upscope $end
$scope module u_rom $end
$var wire 12 { a [11:0] $end
$var wire 1 1 clk $end
$var wire 1 | go $end
$var wire 1 R req $end
$var wire 1 O rst_n $end
$var wire 1 D sel $end
$var parameter 32 } AW $end
$var parameter 88 ~ INIT $end
$var reg 1 Q ack $end
$var reg 32 !" rdata [31:0] $end
$upscope $end
$scope module u_sys $end
$var wire 1 1 clk $end
$var wire 1 "" go $end
$var wire 2 #" reg_a [1:0] $end
$var wire 1 R req $end
$var wire 1 O rst_n $end
$var wire 1 E sel $end
$var wire 32 $" wdata [31:0] $end
$var wire 1 H we $end
$var reg 1 M ack $end
$var reg 4 %" leds [3:0] $end
$var reg 1 V overlay $end
$var reg 32 &" rdata [31:0] $end
$upscope $end
$scope module u_uart $end
$var wire 1 1 clk $end
$var wire 1 '" go $end
$var wire 1 (" reg_a $end
$var wire 1 R req $end
$var wire 1 O rst_n $end
$var wire 1 G rxd $end
$var wire 1 F sel $end
$var wire 32 )" wdata [31:0] $end
$var wire 1 H we $end
$var wire 1 ( txd $end
$var wire 1 *" rxs $end
$var parameter 32 +" BAUD $end
$var parameter 32 ," CLK_HZ $end
$var parameter 32 -" DIV $end
$var reg 1 K ack $end
$var reg 32 ." rdata [31:0] $end
$var reg 1 /" rx_busy $end
$var reg 4 0" rx_cnt [3:0] $end
$var reg 8 1" rx_data [7:0] $end
$var reg 16 2" rx_div [15:0] $end
$var reg 8 3" rx_sh [7:0] $end
$var reg 2 4" rx_sr [1:0] $end
$var reg 1 5" rx_valid $end
$var reg 1 6" tx_busy $end
$var reg 4 7" tx_cnt [3:0] $end
$var reg 16 8" tx_div [15:0] $end
$var reg 10 9" tx_shift [9:0] $end
$upscope $end
$upscope $end
$scope task check $end
$var reg 32 :" exp [31:0] $end
$var reg 32 ;" got [31:0] $end
$var reg 256 <" name [255:0] $end
$upscope $end
$scope task cycle $end
$var reg 32 =" addr [31:0] $end
$var reg 1 >" is_read $end
$var reg 2 ?" size [1:0] $end
$var reg 32 @" wdat [31:0] $end
$var integer 32 A" n [31:0] $end
$upscope $end
$upscope $end
$enddefinitions $end
$comment Show the parameter values. $end
$dumpall
b1010 -"
b10111110101111000010000000 ,"
b10011000100101101000000 +"
b110011001110111001011110110001001101111011011110111010000101110011010000110010101111000 ~
b1100 }
b1101 y
b1 j
b0 i
b10 h
b110011001110111001011110110001001101111011011110111010000101110011010000110010101111000 _
b10111110101111000010000000 ^
b10011000100101101000000 ]
$end
#0
$dumpvars
bx A"
bx @"
bx ?"
x>"
bx ="
bx <"
bx ;"
bx :"
bx 9"
bx 8"
bx 7"
x6"
x5"
bx 4"
bx 3"
bx 2"
bx 1"
bx 0"
x/"
bx ."
x*"
b0 )"
0("
0'"
bx &"
bx %"
b0 $"
b0 #"
0""
bx !"
0|
b0 {
bx z
b0 x
0w
b0 v
b0 u
b0 t
b0 s
b0 r
b0 q
b11 p
b0 o
b1111 n
b0 m
b0 l
b0 k
0g
0f
bx e
b0 d
bz c
b0 b
b0 a
0`
b0 \
b0 [
0Z
b0 Y
b11 X
bx W
xV
xU
bx T
bx S
0R
xQ
bx P
0O
0N
xM
bx L
xK
bx J
b0 I
0H
1G
0F
0E
xD
xC
b0 B
b111 A
bz @
b0 ?
x>
bx =
b0 <
b0 ;
0:
b0 9
18
07
bx 6
x5
b0 4
13
02
01
10
b0 /
1.
0-
0,
0+
b11 *
bx )
x(
1'
b111 &
bz %
1$
1#
1"
1!
$end
#10000
0>
1D
b0 S
b0 e
1*"
1(
0C
b1000000000000000 P
b1000000000000000 !"
0Q
0U
b0xxxxxxxx J
b0xxxxxxxx ."
05"
b0 1"
b0 3"
b0 0"
b0 2"
0/"
b11 4"
b0 8"
b0 7"
b1111111111 9"
06"
0K
b0x L
b0x &"
b0 )
b0 W
b0 %"
1V
0M
1-
1`
11
#20000
01
#30000
0-
0`
b1 L
b1 &"
b0 J
b0 ."
11
#40000
01
#50000
1-
1`
11
#60000
01
#70000
0-
0`
11
#80000
01
#90000
1-
1`
11
#100000
01
17
#110000
b1 a
0-
0`
11
#120000
01
#130000
1-
1`
b10 a
11
#140000
01
#150000
b11 a
0-
0`
11
#160000
01
#170000
1-
1`
b100 a
11
#180000
01
#190000
b101 a
0-
0`
11
#200000
01
#210000
1-
1`
b110 a
11
#220000
01
#230000
b111 a
0-
0`
11
#240000
01
#250000
1-
1`
b1000 a
11
#260000
01
#270000
b1001 a
0-
0`
11
#280000
01
#290000
1-
1`
b1010 a
11
#300000
01
#310000
b1011 a
0-
0`
11
#320000
01
#330000
1-
1`
b1100 a
11
#340000
01
#350000
b1101 a
0-
0`
11
#360000
01
#370000
1-
1`
b1110 a
11
#380000
01
#390000
b1111 a
0-
0`
11
#400000
01
#410000
1-
1`
b10000 a
11
#420000
01
#430000
b10001 a
0-
0`
11
#440000
01
#450000
1-
1`
b10010 a
11
#460000
01
#470000
b10011 a
0-
0`
11
#480000
01
#490000
1-
1`
b10100 a
11
#500000
01
#510000
b10101 a
0-
0`
11
#520000
01
